{
	"info": {
		"_postman_id": "797389f0-def4-45d6-aeb0-c4065db57d9f",
		"name": "semanadiez",
		"schema": "https://schema.getpostman.com/json/collection/v2.1.0/collection.json",
		"_exporter_id": "40416580"
	},
	"item": [
		{
			"name": "autos",
			"item": [
				{
					"name": "List",
					"request": {
						"method": "POST",
						"header": [],
						"url": {
							"raw": "http://localhost:4000/autos/list",
							"protocol": "http",
							"host": [
								"localhost"
							],
							"port": "4000",
							"path": [
								"autos",
								"list"
							]
						}
					},
					"response": []
				},
				{
					"name": "CREATE",
					"request": {
						"method": "POST",
						"header": [],
						"body": {
							"mode": "raw",
							"raw": "{\r\n    \"brand\": \"Camaro\",\r\n    \"npassengers\": \"4\",\r\n    \"color\": \"black\",\r\n    \"nengine\": \"1\",\r\n    \"model\": \"GT\"\r\n}",
							"options": {
								"raw": {
									"language": "json"
								}
							}
						},
						"url": {
							"raw": "http://localhost:4000/autos/create",
							"protocol": "http",
							"host": [
								"localhost"
							],
							"port": "4000",
							"path": [
								"autos",
								"create"
							]
						}
					},
					"response": []
				},
				{
					"name": "UPDATE",
					"request": {
						"method": "POST",
						"header": [],
						"body": {
							"mode": "raw",
							"raw": "{\r\n    \"id\": 1,\r\n    \"brand\": \"BradingCar\",\r\n    \"npassengers\": \"4\",\r\n    \"color\": \"black\",\r\n    \"nengine\": \"2\",\r\n    \"model\": \"GX\"\r\n}",
							"options": {
								"raw": {
									"language": "json"
								}
							}
						},
						"url": {
							"raw": "http://localhost:4000/autos/update",
							"protocol": "http",
							"host": [
								"localhost"
							],
							"port": "4000",
							"path": [
								"autos",
								"update"
							]
						}
					},
					"response": []
				},
				{
					"name": "DELETE",
					"request": {
						"method": "POST",
						"header": [],
						"body": {
							"mode": "raw",
							"raw": "{\r\n    \"id\": 1\r\n}",
							"options": {
								"raw": {
									"language": "json"
								}
							}
						},
						"url": {
							"raw": "http://localhost:4000/autos/delete",
							"protocol": "http",
							"host": [
								"localhost"
							],
							"port": "4000",
							"path": [
								"autos",
								"delete"
							]
						}
					},
					"response": []
				}
			]
		}
	]
}